dask_tensorflow/__init__.py
dask_tensorflow/core.py
dask_tensorflow-0.0.2.dist-info/DESCRIPTION.rst
dask_tensorflow-0.0.2.dist-info/METADATA
dask_tensorflow-0.0.2.dist-info/RECORD
dask_tensorflow-0.0.2.dist-info/WHEEL
dask_tensorflow-0.0.2.dist-info/metadata.json
dask_tensorflow-0.0.2.dist-info/top_level.txt
