Metadata-Version: 2.0
Name: dask-tensorflow
Version: 0.0.2
Summary: Interactions between Dask and Tensorflow
Home-page: UNKNOWN
Author: Matthew Rocklin
Author-email: mrocklin@gmail.com
License: BSD
Platform: UNKNOWN
Requires-Dist: dask
Requires-Dist: distributed
Requires-Dist: tensorflow
